{"meta": {"code": 200, "requestId": "563f0a56498ecdf376616229"}, "response": {"confident": false, "geocode": {"parents": [], "what": "", "where": "prague", "feature": {"highlightedName": "<b>Prague</b>, Czech Republic", "displayName": "Prague, Czech Republic", "name": "Prague", "longId": "72057594040995632", "cc": "CZ", "id": "geonameid:3067696", "geometry": {"center": {"lat": 50.08804, "lng": 14.42076}, "bounds": {"sw": {"lat": 49.942206021440185, "lng": 14.219081000000049}, "ne": {"lat": 50.17753893485459, "lng": 14.71219291017613}}}, "matchedName": "Prague, Czech Republic", "woeType": 7, "slug": "prague-czech-republic"}}, "venues": [{"stats": {"tipCount": 63, "checkinsCount": 2127, "usersCount": 835}, "name": "M\u00edsto", "referralId": "v-1446971991", "venueChains": [], "hereNow": {"count": 1, "groups": [{"count": 1, "items": [], "type": "others", "name": "Other people here"}], "summary": "One other person is here"}, "specials": {"count": 0, "items": []}, "allowMenuUrlEdit": true, "location": {"city": "Praha", "cc": "CZ", "country": "\u010cesk\u00e1 republika", "postalCode": "160 00", "state": "Hlavn\u00ed m\u011bsto Praha", "formattedAddress": ["Bubene\u010dsk\u00e1 284/12 (Jaselsk\u00e1)", "160 00 Praha 6", "\u010cesk\u00e1 republika"], "crossStreet": "Jaselsk\u00e1", "address": "Bubene\u010dsk\u00e1 284/12", "lat": 50.098978646368494, "lng": 14.404248907922012}, "verified": true, "id": "55a776ea498eddbd520275a7", "categories": [{"pluralName": "Caf\u00e9s", "primary": true, "name": "Caf\u00e9", "shortName": "Caf\u00e9", "id": "4bf58dd8d48988d16d941735", "icon": {"prefix": "https://ss3.4sqi.net/img/categories_v2/food/cafe_", "suffix": ".png"}}]}, {"stats": {"tipCount": 111, "checkinsCount": 9616, "usersCount": 3700}, "name": "Bageterie Boulevard", "referralId": "v-1446971991", "venueChains": [], "hereNow": {"count": 1, "groups": [{"count": 1, "items": [], "type": "others", "name": "Other people here"}], "summary": "One other person is here"}, "specials": {"count": 0, "items": []}, "allowMenuUrlEdit": true, "location": {"city": "Praha", "cc": "CZ", "country": "\u010cesk\u00e1 republika", "postalCode": "110 00", "state": "Hlavn\u00ed m\u011bsto Praha", "formattedAddress": ["N\u00e1rodn\u00ed 27 (Na Per\u0161t\u00fdn\u011b)", "110 00 Praha", "\u010cesk\u00e1 republika"], "crossStreet": "Na Per\u0161t\u00fdn\u011b", "address": "N\u00e1rodn\u00ed 27", "lat": 50.08236348389882, "lng": 14.418590068817137}, "verified": false, "id": "5045aef2e4b093fa17c67eec", "categories": [{"pluralName": "Sandwich Places", "primary": true, "name": "Sandwich Place", "shortName": "Sandwiches", "id": "4bf58dd8d48988d1c5941735", "icon": {"prefix": "https://ss3.4sqi.net/img/categories_v2/food/deli_", "suffix": ".png"}}]}, {"stats": {"tipCount": 113, "checkinsCount": 13597, "usersCount": 7437}, "name": "Starbucks", "referralId": "v-1446971991", "venueChains": [{"id": "556f676fbd6a75a99038d8ec"}], "hereNow": {"count": 1, "groups": [{"count": 1, "items": [], "type": "others", "name": "Other people here"}], "summary": "One other person is here"}, "specials": {"count": 0, "items": []}, "allowMenuUrlEdit": true, "location": {"city": "Praha", "cc": "CZ", "country": "\u010cesk\u00e1 republika", "postalCode": "118 00", "state": "Hlavn\u00ed m\u011bsto Praha", "formattedAddress": ["Malostransk\u00e9 n\u00e1m. 5/28", "118 00 Praha", "\u010cesk\u00e1 republika"], "address": "Malostransk\u00e9 n\u00e1m. 5/28", "lat": 50.08797405658672, "lng": 14.404165148735046}, "verified": false, "id": "4b0e3f85f964a5204b5623e3", "categories": [{"pluralName": "Coffee Shops", "primary": true, "name": "Coffee Shop", "shortName": "Coffee Shop", "id": "4bf58dd8d48988d1e0931735", "icon": {"prefix": "https://ss3.4sqi.net/img/categories_v2/food/coffeeshop_", "suffix": ".png"}}]}, {"stats": {"tipCount": 236, "checkinsCount": 11987, "usersCount": 2837}, "name": "EMA espresso bar", "referralId": "v-1446971991", "venueChains": [], "storeId": "", "hereNow": {"count": 0, "groups": [], "summary": "Nobody here"}, "specials": {"count": 0, "items": []}, "allowMenuUrlEdit": true, "location": {"city": "Praha", "cc": "CZ", "country": "\u010cesk\u00e1 republika", "postalCode": "110 00", "state": "Hlavn\u00ed m\u011bsto Praha", "formattedAddress": ["Na Florenci 1420/3", "110 00 Praha", "\u010cesk\u00e1 republika"], "address": "Na Florenci 1420/3", "lat": 50.08863489062585, "lng": 14.4335675239563}, "venuePage": {"id": "59370314"}, "verified": true, "id": "51c70cc3498e0d1d9e1a0087", "categories": [{"pluralName": "Caf\u00e9s", "primary": true, "name": "Caf\u00e9", "shortName": "Caf\u00e9", "id": "4bf58dd8d48988d16d941735", "icon": {"prefix": "https://ss3.4sqi.net/img/categories_v2/food/cafe_", "suffix": ".png"}}]}, {"stats": {"tipCount": 126, "checkinsCount": 23915, "usersCount": 8787}, "name": "ROXY/NoD", "referralId": "v-1446971991", "venueChains": [], "storeId": "", "hereNow": {"count": 0, "groups": [], "summary": "Nobody here"}, "specials": {"count": 0, "items": []}, "allowMenuUrlEdit": true, "location": {"city": "Praha", "cc": "CZ", "country": "\u010cesk\u00e1 republika", "postalCode": "110 00", "state": "Hlavn\u00ed m\u011bsto Praha", "formattedAddress": ["Dlouh\u00e1 33 (Rybn\u00e1)", "110 00 Praha", "\u010cesk\u00e1 republika"], "crossStreet": "Rybn\u00e1", "address": "Dlouh\u00e1 33", "lat": 50.09070682161278, "lng": 14.42579984664917}, "venuePage": {"id": "36568977"}, "verified": true, "id": "4adcda9cf964a5200e4d21e3", "categories": [{"pluralName": "Performing Arts Venues", "primary": true, "name": "Performing Arts Venue", "shortName": "Performing Arts", "id": "4bf58dd8d48988d1f2931735", "icon": {"prefix": "https://ss3.4sqi.net/img/categories_v2/arts_entertainment/performingarts_", "suffix": ".png"}}]}, {"stats": {"tipCount": 150, "checkinsCount": 19068, "usersCount": 4923}, "name": "BIO | OKO", "referralId": "v-1446971991", "venueChains": [], "storeId": "", "hereNow": {"count": 0, "groups": [], "summary": "Nobody here"}, "specials": {"count": 0, "items": []}, "allowMenuUrlEdit": true, "location": {"city": "Praha", "cc": "CZ", "country": "\u010cesk\u00e1 republika", "postalCode": "170 00", "formattedAddress": ["Franti\u0161ka K\u0159\u00ed\u017eka 460/15", "170 00 Praha", "\u010cesk\u00e1 republika"], "address": "Franti\u0161ka K\u0159\u00ed\u017eka 460/15", "lat": 50.09995025945802, "lng": 14.430241584777832}, "venuePage": {"id": "32870539"}, "verified": true, "id": "4b1fe5b7f964a5206f2a24e3", "categories": [{"pluralName": "Indie Movie Theaters", "primary": true, "name": "Indie Movie Theater", "shortName": "Indie Movies", "id": "4bf58dd8d48988d17e941735", "icon": {"prefix": "https://ss3.4sqi.net/img/categories_v2/arts_entertainment/movietheater_", "suffix": ".png"}}]}, {"stats": {"tipCount": 487, "checkinsCount": 22309, "usersCount": 9691}, "name": "Lok\u00e1l Dlouh\u00e1", "referralId": "v-1446971991", "venueChains": [], "hereNow": {"count": 0, "groups": [], "summary": "Nobody here"}, "specials": {"count": 0, "items": []}, "allowMenuUrlEdit": true, "location": {"city": "Praha", "cc": "CZ", "country": "\u010cesk\u00e1 republika", "postalCode": "110 00", "state": "Hlavn\u00ed m\u011bsto Praha", "formattedAddress": ["Dlouh\u00e1 33 (Rybn\u00e1)", "110 00 Praha", "\u010cesk\u00e1 republika"], "crossStreet": "Rybn\u00e1", "address": "Dlouh\u00e1 33", "lat": 50.09066207986333, "lng": 14.425770342350006}, "verified": false, "id": "4af5389cf964a5209af821e3", "categories": [{"pluralName": "Czech Restaurants", "primary": true, "name": "Czech Restaurant", "shortName": "Czech", "id": "52f2ae52bcbc57f1066b8b81", "icon": {"prefix": "https://ss3.4sqi.net/img/categories_v2/food/default_", "suffix": ".png"}}]}, {"stats": {"tipCount": 236, "checkinsCount": 13330, "usersCount": 4792}, "name": "Vinohradsk\u00fd parlament", "referralId": "v-1446971991", "venueChains": [], "hereNow": {"count": 0, "groups": [], "summary": "Nobody here"}, "specials": {"count": 0, "items": []}, "allowMenuUrlEdit": true, "location": {"city": "Praha", "cc": "CZ", "country": "\u010cesk\u00e1 republika", "postalCode": "120 00", "state": "Hlavn\u00ed m\u011bsto Praha", "formattedAddress": ["Korunn\u00ed 1", "120 00 Praha", "\u010cesk\u00e1 republika"], "address": "Korunn\u00ed 1", "lat": 50.07526216708292, "lng": 14.438123982655544}, "verified": false, "id": "51e6a090498e41f4704c04d7", "categories": [{"pluralName": "Czech Restaurants", "primary": true, "name": "Czech Restaurant", "shortName": "Czech", "id": "52f2ae52bcbc57f1066b8b81", "icon": {"prefix": "https://ss3.4sqi.net/img/categories_v2/food/default_", "suffix": ".png"}}]}, {"stats": {"tipCount": 77, "checkinsCount": 4931, "usersCount": 1487}, "name": "Kav\u00e1rna Liber\u00e1l", "referralId": "v-1446971991", "venueChains": [], "hereNow": {"count": 0, "groups": [], "summary": "Nobody here"}, "specials": {"count": 0, "items": []}, "allowMenuUrlEdit": true, "location": {"city": "Praha", "cc": "CZ", "country": "\u010cesk\u00e1 republika", "postalCode": "170 00", "state": "Hlavn\u00ed m\u011bsto Praha", "formattedAddress": ["He\u0159manova 6 (\u0158ez\u00e1\u010dovo n\u00e1m.)", "170 00 Praha", "\u010cesk\u00e1 republika"], "crossStreet": "\u0158ez\u00e1\u010dovo n\u00e1m.", "address": "He\u0159manova 6", "lat": 50.10060118158961, "lng": 14.436128362760929}, "verified": false, "id": "50cf6c48e4b0de306bc516ef", "categories": [{"pluralName": "Caf\u00e9s", "primary": true, "name": "Caf\u00e9", "shortName": "Caf\u00e9", "id": "4bf58dd8d48988d16d941735", "icon": {"prefix": "https://ss3.4sqi.net/img/categories_v2/food/cafe_", "suffix": ".png"}}]}, {"stats": {"tipCount": 7, "checkinsCount": 6861, "usersCount": 444}, "name": "Biliard Club U Br\u00e1ny", "referralId": "v-1446971991", "venueChains": [], "hereNow": {"count": 0, "groups": [], "summary": "Nobody here"}, "specials": {"count": 0, "items": []}, "allowMenuUrlEdit": true, "location": {"city": "Beroun", "cc": "CZ", "country": "\u010cesk\u00e1 republika", "state": "St\u0159edo\u010desk\u00fd", "formattedAddress": ["V Pra\u017esk\u00e9 br\u00e1n\u011b 4", "Beroun", "\u010cesk\u00e1 republika"], "address": "V Pra\u017esk\u00e9 br\u00e1n\u011b 4", "lat": 49.96406534369177, "lng": 14.075299501419067}, "verified": false, "id": "4cadbb68632b3704dc77696e", "categories": [{"pluralName": "Pool Halls", "primary": true, "name": "Pool Hall", "shortName": "Billiards", "id": "4bf58dd8d48988d1e3931735", "icon": {"prefix": "https://ss3.4sqi.net/img/categories_v2/arts_entertainment/billiards_", "suffix": ".png"}}]}, {"stats": {"tipCount": 101, "checkinsCount": 2319, "usersCount": 1039}, "name": "AnonymouS Coffee", "referralId": "v-1446971991", "venueChains": [{"id": "556e5660bd6a82902e28a46c"}], "storeId": "", "hereNow": {"count": 0, "groups": [], "summary": "Nobody here"}, "specials": {"count": 0, "items": []}, "allowMenuUrlEdit": true, "location": {"city": "Praha", "cc": "CZ", "country": "\u010cesk\u00e1 republika", "postalCode": "12000", "state": "Hlavn\u00ed m\u011bsto Praha", "formattedAddress": ["Jugosl\u00e1vsk\u00e1 15 (Lond\u00fdnsk\u00e1)", "12000 Praha", "\u010cesk\u00e1 republika"], "crossStreet": "Lond\u00fdnsk\u00e1", "address": "Jugosl\u00e1vsk\u00e1 15", "lat": 50.075392940533, "lng": 14.432648213720825}, "verified": true, "id": "540d7377498ebc7a3b4ccb55", "categories": [{"pluralName": "Coffee Shops", "primary": true, "name": "Coffee Shop", "shortName": "Coffee Shop", "id": "4bf58dd8d48988d1e0931735", "icon": {"prefix": "https://ss3.4sqi.net/img/categories_v2/food/coffeeshop_", "suffix": ".png"}}]}, {"stats": {"tipCount": 116, "checkinsCount": 9485, "usersCount": 2152}, "name": "Alza Caf\u00e9", "referralId": "v-1446971991", "venueChains": [{"id": "556e5d4dbd6a82902e2991db"}], "storeId": "", "hereNow": {"count": 0, "groups": [], "summary": "Nobody here"}, "specials": {"count": 0, "items": []}, "allowMenuUrlEdit": true, "location": {"city": "Praha", "cc": "CZ", "country": "\u010cesk\u00e1 republika", "postalCode": "170 00", "state": "Hlavn\u00ed m\u011bsto Praha", "formattedAddress": ["Jate\u010dn\u00ed 33", "170 00 Praha", "\u010cesk\u00e1 republika"], "address": "Jate\u010dn\u00ed 33", "lat": 50.10019801136036, "lng": 14.447922706604004}, "verified": true, "id": "50cf071ae4b0ed7c490df0cc", "categories": [{"pluralName": "Caf\u00e9s", "primary": true, "name": "Caf\u00e9", "shortName": "Caf\u00e9", "id": "4bf58dd8d48988d16d941735", "icon": {"prefix": "https://ss3.4sqi.net/img/categories_v2/food/cafe_", "suffix": ".png"}}]}, {"stats": {"tipCount": 62, "checkinsCount": 4803, "usersCount": 1739}, "name": "Lok\u00e1l Hamburk", "referralId": "v-1446971991", "venueChains": [], "hereNow": {"count": 0, "groups": [], "summary": "Nobody here"}, "specials": {"count": 0, "items": []}, "allowMenuUrlEdit": true, "location": {"city": "Praha", "cc": "CZ", "country": "\u010cesk\u00e1 republika", "state": "Hlavn\u00ed m\u011bsto Praha", "formattedAddress": ["Sokolovsk\u00e1 55 (U n\u00e1dra\u017en\u00ed l\u00e1vky)", "Praha", "\u010cesk\u00e1 republika"], "crossStreet": "U n\u00e1dra\u017en\u00ed l\u00e1vky", "address": "Sokolovsk\u00e1 55", "lat": 50.09293117461007, "lng": 14.446447534071622}, "verified": false, "id": "538dc3de498eecce5c700599", "categories": [{"pluralName": "Czech Restaurants", "primary": true, "name": "Czech Restaurant", "shortName": "Czech", "id": "52f2ae52bcbc57f1066b8b81", "icon": {"prefix": "https://ss3.4sqi.net/img/categories_v2/food/default_", "suffix": ".png"}}]}, {"stats": {"tipCount": 108, "checkinsCount": 10591, "usersCount": 4115}, "name": "Bageterie Boulevard", "referralId": "v-1446971991", "venueChains": [], "hereNow": {"count": 0, "groups": [], "summary": "Nobody here"}, "specials": {"count": 0, "items": []}, "allowMenuUrlEdit": true, "location": {"city": "Praha", "cc": "CZ", "country": "\u010cesk\u00e1 republika", "postalCode": "11000", "state": "Hlavn\u00ed m\u011bsto Praha", "formattedAddress": ["Vodi\u010dkova 727/21", "11000 Praha", "\u010cesk\u00e1 republika"], "address": "Vodi\u010dkova 727/21", "lat": 50.08060273015763, "lng": 14.423863291740416}, "verified": false, "id": "4b659c02f964a5204bf62ae3", "categories": [{"pluralName": "Sandwich Places", "primary": true, "name": "Sandwich Place", "shortName": "Sandwiches", "id": "4bf58dd8d48988d1c5941735", "icon": {"prefix": "https://ss3.4sqi.net/img/categories_v2/food/deli_", "suffix": ".png"}}]}, {"stats": {"tipCount": 191, "checkinsCount": 10929, "usersCount": 4502}, "name": "Restaurace Hybernia", "referralId": "v-1446971991", "venueChains": [], "hereNow": {"count": 0, "groups": [], "summary": "Nobody here"}, "specials": {"count": 0, "items": []}, "allowMenuUrlEdit": true, "location": {"city": "Praha", "cc": "CZ", "country": "\u010cesk\u00e1 republika", "postalCode": "110 00", "state": "Hlavn\u00ed m\u011bsto Praha", "formattedAddress": ["Hybernsk\u00e1 7/1033", "110 00 Praha", "\u010cesk\u00e1 republika"], "address": "Hybernsk\u00e1 7/1033", "lat": 50.087418591168884, "lng": 14.43145479409745}, "verified": false, "id": "4b17b472f964a5204ec723e3", "categories": [{"pluralName": "Eastern European Restaurants", "primary": true, "name": "Eastern European Restaurant", "shortName": "Eastern European", "id": "4bf58dd8d48988d109941735", "icon": {"prefix": "https://ss3.4sqi.net/img/categories_v2/food/default_", "suffix": ".png"}}]}, {"stats": {"tipCount": 57, "checkinsCount": 3833, "usersCount": 1290}, "name": "Delmart", "referralId": "v-1446971991", "venueChains": [], "hereNow": {"count": 0, "groups": [], "summary": "Nobody here"}, "specials": {"count": 0, "items": []}, "allowMenuUrlEdit": true, "location": {"city": "Praha", "cc": "CZ", "country": "\u010cesk\u00e1 republika", "postalCode": "150 00", "state": "Hlavn\u00ed m\u011bsto Praha", "formattedAddress": ["N\u00e1dra\u017en\u00ed 27", "150 00 Praha", "\u010cesk\u00e1 republika"], "address": "N\u00e1dra\u017en\u00ed 27", "lat": 50.07134699516897, "lng": 14.40423032069454}, "verified": false, "id": "53cfa7a1498eeedf49be439d", "categories": [{"pluralName": "Gourmet Shops", "primary": true, "name": "Gourmet Shop", "shortName": "Gourmet", "id": "4bf58dd8d48988d1f5941735", "icon": {"prefix": "https://ss3.4sqi.net/img/categories_v2/shops/food_gourmet_", "suffix": ".png"}}]}, {"stats": {"tipCount": 167, "checkinsCount": 6006, "usersCount": 2113}, "name": "Na\u0161e maso", "referralId": "v-1446971991", "venueChains": [], "hereNow": {"count": 0, "groups": [], "summary": "Nobody here"}, "specials": {"count": 0, "items": []}, "allowMenuUrlEdit": true, "location": {"city": "Praha", "cc": "CZ", "country": "\u010cesk\u00e1 republika", "postalCode": "110 00", "state": "Hlavn\u00ed m\u011bsto Praha", "formattedAddress": ["Dlouh\u00e1 727/39", "110 00 Praha", "\u010cesk\u00e1 republika"], "address": "Dlouh\u00e1 727/39", "lat": 50.09067219444903, "lng": 14.426940555325606}, "verified": false, "id": "5311ae7311d2b14c76832d24", "categories": [{"pluralName": "Butchers", "primary": true, "name": "Butcher", "shortName": "Butcher", "id": "4bf58dd8d48988d11d951735", "icon": {"prefix": "https://ss3.4sqi.net/img/categories_v2/shops/food_butcher_", "suffix": ".png"}}]}, {"stats": {"tipCount": 55, "checkinsCount": 9269, "usersCount": 3462}, "name": "TTTM Sapa (Mal\u00e1 Hanoj)", "referralId": "v-1446971991", "venueChains": [], "hereNow": {"count": 0, "groups": [], "summary": "Nobody here"}, "specials": {"count": 0, "items": []}, "allowMenuUrlEdit": true, "location": {"city": "Praha", "cc": "CZ", "country": "\u010cesk\u00e1 republika", "postalCode": "148 00", "state": "Hlavn\u00ed m\u011bsto Praha", "formattedAddress": ["Libu\u0161sk\u00e1 319/126", "148 00 Praha", "\u010cesk\u00e1 republika"], "address": "Libu\u0161sk\u00e1 319/126", "lat": 50.00329137087573, "lng": 14.473081827163696}, "verified": false, "id": "4b360a90f964a520d62f25e3", "categories": [{"pluralName": "Malls", "primary": true, "name": "Mall", "shortName": "Mall", "id": "4bf58dd8d48988d1fd941735", "icon": {"prefix": "https://ss3.4sqi.net/img/categories_v2/shops/mall_", "suffix": ".png"}}]}, {"stats": {"tipCount": 224, "checkinsCount": 17031, "usersCount": 4272}, "name": "Wine Food Market", "referralId": "v-1446971991", "venueChains": [], "hereNow": {"count": 0, "groups": [], "summary": "Nobody here"}, "specials": {"count": 0, "items": []}, "allowMenuUrlEdit": true, "location": {"city": "Praha", "cc": "CZ", "country": "\u010cesk\u00e1 republika", "postalCode": "150 00", "state": "Hlavn\u00ed m\u011bsto Praha", "formattedAddress": ["Strakonick\u00e1 1 (U Kr\u00e1lovsk\u00e9 louky)", "150 00 Praha", "\u010cesk\u00e1 republika"], "crossStreet": "U Kr\u00e1lovsk\u00e9 louky", "address": "Strakonick\u00e1 1", "lat": 50.06310043884741, "lng": 14.4102063428292}, "verified": false, "id": "4c53013e94790f477e506aa3", "categories": [{"pluralName": "Gourmet Shops", "primary": true, "name": "Gourmet Shop", "shortName": "Gourmet", "id": "4bf58dd8d48988d1f5941735", "icon": {"prefix": "https://ss3.4sqi.net/img/categories_v2/shops/food_gourmet_", "suffix": ".png"}}]}, {"stats": {"tipCount": 134, "checkinsCount": 15938, "usersCount": 2136}, "name": "Avion 58", "referralId": "v-1446971991", "venueChains": [], "hereNow": {"count": 0, "groups": [], "summary": "Nobody here"}, "specials": {"count": 0, "items": []}, "allowMenuUrlEdit": true, "location": {"city": "Praha", "cc": "CZ", "country": "\u010cesk\u00e1 republika", "postalCode": "170 00", "state": "Hlavn\u00ed m\u011bsto Praha", "formattedAddress": ["Komunard\u016f 42", "170 00 Praha", "\u010cesk\u00e1 republika"], "address": "Komunard\u016f 42", "lat": 50.105716, "lng": 14.450876}, "verified": false, "id": "4d49242a031f5941b005efc0", "categories": [{"pluralName": "Restaurants", "primary": true, "name": "Restaurant", "shortName": "Restaurant", "id": "4bf58dd8d48988d1c4941735", "icon": {"prefix": "https://ss3.4sqi.net/img/categories_v2/food/default_", "suffix": ".png"}}]}, {"stats": {"tipCount": 343, "checkinsCount": 23439, "usersCount": 17948}, "name": "Hard Rock Cafe Praha", "referralId": "v-1446971991", "venueChains": [{"id": "556a337ba7c8957d73d4b6b4"}], "storeId": "", "hereNow": {"count": 0, "groups": [], "summary": "Nobody here"}, "specials": {"count": 0, "items": []}, "allowMenuUrlEdit": true, "location": {"city": "Praha", "cc": "CZ", "country": "\u010cesk\u00e1 republika", "postalCode": "110 00", "state": "Hlavn\u00ed m\u011bsto Praha", "formattedAddress": ["Mal\u00e9 N\u00e1m\u011bst\u00ed 3 (D\u016fm u Rotta)", "110 00 Praha", "\u010cesk\u00e1 republika"], "crossStreet": "D\u016fm u Rotta", "address": "Mal\u00e9 N\u00e1m\u011bst\u00ed 3", "lat": 50.08665580313519, "lng": 14.419265985488892}, "verified": true, "id": "4b4c87eaf964a52049b526e3", "categories": [{"pluralName": "American Restaurants", "primary": true, "name": "American Restaurant", "shortName": "American", "id": "4bf58dd8d48988d14e941735", "icon": {"prefix": "https://ss3.4sqi.net/img/categories_v2/food/default_", "suffix": ".png"}}]}, {"stats": {"tipCount": 148, "checkinsCount": 9413, "usersCount": 2524}, "name": "Pho Vietnam Tuan & Lan", "referralId": "v-1446971991", "venueChains": [], "hereNow": {"count": 0, "groups": [], "summary": "Nobody here"}, "specials": {"count": 0, "items": []}, "allowMenuUrlEdit": true, "location": {"city": "Praha", "cc": "CZ", "country": "\u010cesk\u00e1 republika", "postalCode": "120 00", "state": "Hlavn\u00ed m\u011bsto Praha", "formattedAddress": ["Anglick\u00e1 529/15", "120 00 Praha", "\u010cesk\u00e1 republika"], "address": "Anglick\u00e1 529/15", "lat": 50.076758340010414, "lng": 14.432989686159829}, "verified": false, "id": "4fface89e4b0a0306dbfd10e", "categories": [{"pluralName": "Vietnamese Restaurants", "primary": true, "name": "Vietnamese Restaurant", "shortName": "Vietnamese", "id": "4bf58dd8d48988d14a941735", "icon": {"prefix": "https://ss3.4sqi.net/img/categories_v2/food/vietnamese_", "suffix": ".png"}}]}, {"stats": {"tipCount": 387, "checkinsCount": 19405, "usersCount": 8846}, "name": "Caf\u00e9 Louvre", "referralId": "v-1446971991", "venueChains": [], "hereNow": {"count": 0, "groups": [], "summary": "Nobody here"}, "specials": {"count": 0, "items": []}, "allowMenuUrlEdit": true, "location": {"city": "Praha", "cc": "CZ", "country": "\u010cesk\u00e1 republika", "postalCode": "110 00", "state": "Hlavn\u00ed m\u011bsto Praha", "formattedAddress": ["N\u00e1rodn\u00ed 22", "110 00 Praha", "\u010cesk\u00e1 republika"], "address": "N\u00e1rodn\u00ed 22", "lat": 50.0822565228983, "lng": 14.41861210096352}, "verified": true, "id": "4af48deaf964a520caf321e3", "categories": [{"pluralName": "Caf\u00e9s", "primary": true, "name": "Caf\u00e9", "shortName": "Caf\u00e9", "id": "4bf58dd8d48988d16d941735", "icon": {"prefix": "https://ss3.4sqi.net/img/categories_v2/food/cafe_", "suffix": ".png"}}]}, {"stats": {"tipCount": 123, "checkinsCount": 2221, "usersCount": 1156}, "name": "The Farm Letna", "referralId": "v-1446971991", "venueChains": [], "hereNow": {"count": 0, "groups": [], "summary": "Nobody here"}, "specials": {"count": 0, "items": []}, "allowMenuUrlEdit": true, "location": {"city": "Praha", "cc": "CZ", "country": "\u010cesk\u00e1 republika", "postalCode": "17000", "state": "Hlavn\u00ed m\u011bsto Praha", "formattedAddress": ["Korunova\u010dn\u00ed 923/17", "17000 Praha", "\u010cesk\u00e1 republika"], "address": "Korunova\u010dn\u00ed 923/17", "lat": 50.101003196194306, "lng": 14.418203830718994}, "verified": false, "id": "53569df5498ea6451e5e5e0d", "categories": [{"pluralName": "Caf\u00e9s", "primary": true, "name": "Caf\u00e9", "shortName": "Caf\u00e9", "id": "4bf58dd8d48988d16d941735", "icon": {"prefix": "https://ss3.4sqi.net/img/categories_v2/food/cafe_", "suffix": ".png"}}]}, {"stats": {"tipCount": 133, "checkinsCount": 10521, "usersCount": 3672}, "name": "Groove Bar", "referralId": "v-1446971991", "venueChains": [], "storeId": "", "hereNow": {"count": 0, "groups": [], "summary": "Nobody here"}, "specials": {"count": 0, "items": []}, "allowMenuUrlEdit": true, "location": {"city": "Praha", "cc": "CZ", "country": "\u010cesk\u00e1 republika", "postalCode": "110 00", "state": "Hlavn\u00ed m\u011bsto Praha", "formattedAddress": ["Vor\u0161ilsk\u00e1 6", "110 00 Praha", "\u010cesk\u00e1 republika"], "address": "Vor\u0161ilsk\u00e1 6", "lat": 50.080499, "lng": 14.4169788}, "venuePage": {"id": "64895745"}, "verified": true, "id": "4c1426edb7b9c928baecaa37", "categories": [{"pluralName": "Cocktail Bars", "primary": true, "name": "Cocktail Bar", "shortName": "Cocktail", "id": "4bf58dd8d48988d11e941735", "icon": {"prefix": "https://ss3.4sqi.net/img/categories_v2/nightlife/cocktails_", "suffix": ".png"}}]}, {"stats": {"tipCount": 135, "checkinsCount": 5649, "usersCount": 1314}, "name": "Anton\u00ednovo peka\u0159stv\u00ed", "referralId": "v-1446971991", "venueChains": [], "storeId": "", "hereNow": {"count": 0, "groups": [], "summary": "Nobody here"}, "specials": {"count": 1, "items": [{"redemption": "webview", "description": "", "unlocked": true, "photo": {"suffix": "/78113662_nSZfRwL1Dpu14qSX47VzziARhdVXqIn5NuqExfVR06Q.jpg", "height": 720, "width": 960, "prefix": "https://irs1.4sqi.net/img/general/", "id": "531a0aa311d2a07a46393678", "createdAt": 1394215587}, "title": "Special", "page": {"bio": "", "firstName": "Anton\u00ednovo peka\u0159stv\u00ed", "gender": "none", "venue": {"id": "52d6a18c498ec7f9b33c8c98"}, "lists": {"groups": [{"count": 2, "items": [], "type": "created"}]}, "homeCity": "Praha, Hlavn\u00ed m\u011bsto Praha", "contact": {}, "photo": {"prefix": "https://irs1.4sqi.net/img/user/", "suffix": "/78113662-KS0L23LYNFY3ALRF.png"}, "tips": {"count": 3}, "type": "venuePage", "id": "78113662"}, "state": "unlocked", "interaction": {"entryUrl": "https://foursquare.com/device/specials/531a0aa3498e8f9d8c7f9543?venueId=52d6a18c498ec7f9b33c8c98"}, "provider": "foursquare", "message": "Poka\u017ed\u00e9, kdy\u017e se u n\u00e1s checkne\u0161, dostane\u0161 od n\u00e1s malou pozornost - ke ka\u017ed\u00e9 k\u00e1v\u011b od n\u00e1s zdarma dostane\u0161 lineck\u00e9 srd\u00ed\u010dko :-)", "type": "frequency", "id": "531a0aa3498e8f9d8c7f9543", "icon": "default"}]}, "allowMenuUrlEdit": true, "location": {"city": "Praha", "neighborhood": "Vinohrady", "cc": "CZ", "country": "\u010cesk\u00e1 republika", "postalCode": "13000", "state": "Hlavn\u00ed m\u011bsto Praha", "formattedAddress": ["Laubova 4", "13000 Praha", "\u010cesk\u00e1 republika"], "address": "Laubova 4", "lat": 50.078827411845786, "lng": 14.450102084461822}, "venuePage": {"id": "78113662"}, "verified": true, "id": "52d6a18c498ec7f9b33c8c98", "categories": [{"pluralName": "Bakeries", "primary": true, "name": "Bakery", "shortName": "Bakery", "id": "4bf58dd8d48988d16a941735", "icon": {"prefix": "https://ss3.4sqi.net/img/categories_v2/food/bakery_", "suffix": ".png"}}]}, {"stats": {"tipCount": 91, "checkinsCount": 10995, "usersCount": 2358}, "name": "Standard Cafe", "referralId": "v-1446971991", "venueChains": [], "hereNow": {"count": 0, "groups": [], "summary": "Nobody here"}, "specials": {"count": 0, "items": []}, "allowMenuUrlEdit": true, "location": {"city": "Praha", "cc": "CZ", "country": "\u010cesk\u00e1 republika", "postalCode": "110 00", "state": "Hlavn\u00ed m\u011bsto Praha", "formattedAddress": ["Karoliny Sv\u011btl\u00e9 321/23", "110 00 Praha", "\u010cesk\u00e1 republika"], "address": "Karoliny Sv\u011btl\u00e9 321/23", "lat": 50.08335, "lng": 14.414504950000001}, "verified": false, "id": "4d4ec268deabf04d5da8c524", "categories": [{"pluralName": "Caf\u00e9s", "primary": true, "name": "Caf\u00e9", "shortName": "Caf\u00e9", "id": "4bf58dd8d48988d16d941735", "icon": {"prefix": "https://ss3.4sqi.net/img/categories_v2/food/cafe_", "suffix": ".png"}}]}, {"stats": {"tipCount": 389, "checkinsCount": 20073, "usersCount": 4562}, "name": "M\u016fj \u0161\u00e1lek k\u00e1vy", "referralId": "v-1446971991", "venueChains": [{"id": "556e5d4dbd6a82902e2991db"}], "storeId": "", "hereNow": {"count": 0, "groups": [], "summary": "Nobody here"}, "specials": {"count": 0, "items": []}, "allowMenuUrlEdit": true, "location": {"city": "Praha", "cc": "CZ", "country": "\u010cesk\u00e1 republika", "postalCode": "186 00", "state": "Hlavn\u00ed m\u011bsto Praha", "formattedAddress": ["K\u0159i\u017e\u00edkova 105", "186 00 Praha", "\u010cesk\u00e1 republika"], "address": "K\u0159i\u017e\u00edkova 105", "lat": 50.09344081547644, "lng": 14.45501384027034}, "verified": true, "id": "4dac1aa1f7b145b370333acf", "categories": [{"pluralName": "Caf\u00e9s", "primary": true, "name": "Caf\u00e9", "shortName": "Caf\u00e9", "id": "4bf58dd8d48988d16d941735", "icon": {"prefix": "https://ss3.4sqi.net/img/categories_v2/food/cafe_", "suffix": ".png"}}]}, {"stats": {"tipCount": 78, "checkinsCount": 5945, "usersCount": 1874}, "name": "Lok\u00e1l Nad Stromovkou", "referralId": "v-1446971991", "venueChains": [], "hereNow": {"count": 0, "groups": [], "summary": "Nobody here"}, "specials": {"count": 0, "items": []}, "allowMenuUrlEdit": true, "location": {"city": "Praha", "cc": "CZ", "country": "\u010cesk\u00e1 republika", "postalCode": "170 00", "state": "Hlavn\u00ed m\u011bsto Praha", "formattedAddress": ["Nad Kr\u00e1lovskou oborou 232/31", "170 00 Praha", "\u010cesk\u00e1 republika"], "address": "Nad Kr\u00e1lovskou oborou 232/31", "lat": 50.10310555945817, "lng": 14.418375492095947}, "verified": false, "id": "51a4323d7dd246514eaf73ee", "categories": [{"pluralName": "Czech Restaurants", "primary": true, "name": "Czech Restaurant", "shortName": "Czech", "id": "52f2ae52bcbc57f1066b8b81", "icon": {"prefix": "https://ss3.4sqi.net/img/categories_v2/food/default_", "suffix": ".png"}}]}, {"stats": {"tipCount": 298, "checkinsCount": 18961, "usersCount": 9964}, "name": "James Dean Prague", "referralId": "v-1446971991", "venueChains": [], "hereNow": {"count": 0, "groups": [], "summary": "Nobody here"}, "specials": {"count": 0, "items": []}, "allowMenuUrlEdit": true, "location": {"city": "Praha", "cc": "CZ", "country": "\u010cesk\u00e1 republika", "postalCode": "110 00", "state": "Hlavn\u00ed m\u011bsto Praha", "formattedAddress": ["V kolkovn\u011b 922/1 (Dlouh\u00e1)", "110 00 Praha", "\u010cesk\u00e1 republika"], "crossStreet": "Dlouh\u00e1", "address": "V kolkovn\u011b 922/1", "lat": 50.08955060011966, "lng": 14.422406679806857}, "verified": false, "id": "4ed77ae5b6346530d066964c", "categories": [{"pluralName": "American Restaurants", "primary": true, "name": "American Restaurant", "shortName": "American", "id": "4bf58dd8d48988d14e941735", "icon": {"prefix": "https://ss3.4sqi.net/img/categories_v2/food/default_", "suffix": ".png"}}]}]}}